{
  "main": {
    "id": "7466821a4fe72577",
    "type": "split",
    "children": [
      {
        "id": "d13d0075181ff0c4",
        "type": "tabs",
        "children": [
          {
            "id": "88b4ed257672bd2d",
            "type": "leaf",
            "state": {
              "type": "empty",
              "state": {},
              "icon": "lucide-file",
              "title": "New tab"
            }
          }
        ]
      }
    ],
    "direction": "vertical"
  },
  "left": {
    "id": "0fe995036468e3b5",
    "type": "split",
    "children": [
      {
        "id": "e44c1713f7e831b2",
        "type": "tabs",
        "children": [
          {
            "id": "61a29ac0d3d1ca10",
            "type": "leaf",
            "state": {
              "type": "file-explorer",
              "state": {
                "sortOrder": "alphabetical",
                "autoReveal": false
              },
              "icon": "lucide-folder-closed",
              "title": "Files"
            }
          },
          {
            "id": "7dafc9ce2d476bd7",
            "type": "leaf",
            "state": {
              "type": "search",
              "state": {
                "query": "",
                "matchingCase": false,
                "explainSearch": false,
                "collapseAll": false,
                "extraContext": false,
                "sortOrder": "alphabetical"
              },
              "icon": "lucide-search",
              "title": "Search"
            }
          },
          {
            "id": "b045bcd1a3fb0237",
            "type": "leaf",
            "state": {
              "type": "bookmarks",
              "state": {},
              "icon": "lucide-bookmark",
              "title": "Bookmarks"
            }
          }
        ]
      }
    ],
    "direction": "horizontal",
    "width": 297.5
  },
  "right": {
    "id": "e2edfdd285465075",
    "type": "split",
    "children": [
      {
        "id": "6140f0c2b80d525e",
        "type": "tabs",
        "children": [
          {
            "id": "2edcd0ba32440cfa",
            "type": "leaf",
            "state": {
              "type": "backlink",
              "state": {
                "collapseAll": false,
                "extraContext": false,
                "sortOrder": "alphabetical",
                "showSearch": false,
                "searchQuery": "",
                "backlinkCollapsed": false,
                "unlinkedCollapsed": true
              },
              "icon": "links-coming-in",
              "title": "Backlinks"
            }
          },
          {
            "id": "55ce9243711cc63b",
            "type": "leaf",
            "state": {
              "type": "outgoing-link",
              "state": {
                "linksCollapsed": false,
                "unlinkedCollapsed": true
              },
              "icon": "links-going-out",
              "title": "Outgoing links"
            }
          },
          {
            "id": "d8b8e5788ce2785d",
            "type": "leaf",
            "state": {
              "type": "tag",
              "state": {
                "sortOrder": "frequency",
                "useHierarchy": true,
                "showSearch": false,
                "searchQuery": ""
              },
              "icon": "lucide-tags",
              "title": "Tags"
            }
          },
          {
            "id": "53c154b6ec72f75f",
            "type": "leaf",
            "state": {
              "type": "outline",
              "state": {
                "followCursor": false,
                "showSearch": false,
                "searchQuery": ""
              },
              "icon": "lucide-list",
              "title": "Outline"
            }
          },
          {
            "id": "b413fd4eaf05329f",
            "type": "leaf",
            "state": {
              "type": "advanced-tables-toolbar",
              "state": {},
              "icon": "spreadsheet",
              "title": "Advanced Tables"
            }
          }
        ],
        "currentTab": 4
      }
    ],
    "direction": "horizontal",
    "width": 300,
    "collapsed": true
  },
  "left-ribbon": {
    "hiddenItems": {
      "bases:Create new base": false,
      "switcher:Open quick switcher": false,
      "graph:Open graph view": false,
      "canvas:Create new canvas": true,
      "templates:Insert template": true,
      "command-palette:Open command palette": true,
      "obsidian-excalidraw-plugin:New drawing": false,
      "table-editor-obsidian:Advanced Tables Toolbar": false
    }
  },
  "active": "88b4ed257672bd2d",
  "lastOpenFiles": [
    "engineering/programming-languages/javascript-typescript/nodebook.md",
    "attachments/Pasted image 20260615152905.png",
    "english/english grammar in use.md",
    "engineering/roadmaps/low-level system engineer.md",
    "english",
    "computer-science/algorithms/tree.md",
    "computer-science/algorithms/segment tree.md",
    "engineering/programming-languages/javascript-typescript/asynchronous task runner.md",
    "engineering/infrastructure/k8s.md",
    "engineering/infrastructure/k8s.md.tmp.16531.c4558cc78988",
    "engineering/infrastructure/k8s.md.tmp.16531.2832b2a79aa3",
    "engineering/infrastructure/k8s.md.tmp.16531.b66c5f4f7457",
    "engineering/infrastructure/k8s.md.tmp.16531.556ff241d74f",
    "engineering/infrastructure/k8s.md.tmp.16531.4e220863cf73",
    "engineering/infrastructure/k8s.md.tmp.16531.26448bfa4026",
    "engineering/infrastructure/k8s.md.tmp.16531.d97685971ae3",
    "engineering/infrastructure/k8s.md.tmp.16531.946fa623941b",
    "engineering/infrastructure/k8s.md.tmp.16531.9bcf8de15e54",
    "engineering/infrastructure/gcp.md",
    "engineering/system-architecture/hexagon.md",
    "engineering/programming-languages/javascript-typescript/javascript-info.md",
    "excalidraw/consistent-hashing-drawing.md",
    "excalidraw/AWS VPC.md",
    "excalidraw/cache-data-inconsistency.md",
    "excalidraw/GCP - Network endpoint group.md",
    "excalidraw/serverless & NAT.md",
    "engineering/storage engine/lsm.md",
    "computer-science/database/database internals/lsm.md",
    "engineering/system-design/CAP theorem.md",
    "engineering/system-design/cqrs.md",
    "engineering/system-design/outbox.md",
    "engineering/system-design/saga.md",
    "engineering/system-design/idempotency.md",
    "engineering/system-design/sloppy quorum - hinted handoff.md",
    "engineering/system-design/search autocomplete - incremental search.md",
    "engineering/system-design/gossip protocol.md",
    "attachments/Pasted image 20260321120728.png",
    "attachments/Pasted image 20260321120525.png",
    "attachments/Pasted image 20260221171610.png",
    "attachments/Pasted image 20260221163813.png",
    "attachments/Pasted image 20260220164004.png",
    "attachments/Pasted image 20260216003547.png",
    "attachments/Pasted image 20260216002137.png",
    "attachments/Pasted image 20260216001208.png",
    "attachments/Pasted image 20260215234227.png",
    "Untitled.canvas"
  ]
}